rohrpost/__init__.py
rohrpost/handlers.py
rohrpost/main.py
rohrpost/message.py
rohrpost/mixins.py
rohrpost/py.typed
rohrpost/registry.py
rohrpost/sync_consumer.py
rohrpost/tests.py
rohrpost-4.1.0.dist-info/LICENSE
rohrpost-4.1.0.dist-info/METADATA
rohrpost-4.1.0.dist-info/WHEEL
rohrpost-4.1.0.dist-info/top_level.txt
rohrpost-4.1.0.dist-info/RECORD
