Metadata-Version: 2.1
Name: rohrpost
Version: 4.1.0
Summary: rohrpost WebSocket protocol for ASGI
Author-email: Tobias Kunze <tobias.kunze@ax-semantics.com>
License: MIT
Project-URL: Documentation, https://rohrpost.readthedocs.io/en/stable/
Project-URL: Changelog, https://github.com/axsemantics/rohrpost/blob/main/CHANGELOG.rst
Project-URL: Source, https://github.com/axsemantics/rohrpost
Project-URL: Tracker, https://github.com/axsemantics/rohrpost/issues
Classifier: Development Status :: 5 - Production/Stable
Classifier: Environment :: Web Environment
Classifier: Intended Audience :: Developers
Classifier: Operating System :: OS Independent
Classifier: License :: OSI Approved :: MIT License
Classifier: Programming Language :: Python :: 3
Classifier: Programming Language :: Python :: 3.8
Classifier: Programming Language :: Python :: 3.9
Classifier: Programming Language :: Python :: 3.10
Classifier: Programming Language :: Python :: 3.11
Classifier: Programming Language :: Python :: 3.12
Classifier: Programming Language :: Python :: 3.13
Classifier: Programming Language :: Python :: 3 :: Only
Classifier: Topic :: Internet :: WWW/HTTP
Requires-Python: >=3.8
License-File: LICENSE
Requires-Dist: channels>=4.0
